feedly/__init__.py
feedly/client.py
python_feedly-1.1.0.dist-info/METADATA
python_feedly-1.1.0.dist-info/RECORD
python_feedly-1.1.0.dist-info/WHEEL
python_feedly-1.1.0.dist-info/top_level.txt
