Metadata-Version: 2.1
Name: python-feedly
Version: 1.1.0
Summary: Client for Feedly.com
Home-page: https://github.com/WarmongeR1/python-feedly
Author: Alexander Sapronov
Author-email: sapronov.alexander92@gmail.com
License: The MIT License (MIT)
Requires-Dist: requests
